astro/__init__.py
astro/constants.py
astro/exceptions.py
astro/options.py
astro/query_modifier.py
astro/settings.py
astro/table.py
astro/airflow/__init__.py
astro/airflow/datasets.py
astro/custom_backend/__init__.py
astro/custom_backend/astro_custom_backend.py
astro/custom_backend/serializer.py
astro/databases/__init__.py
astro/databases/base.py
astro/databases/duckdb.py
astro/databases/mssql.py
astro/databases/mysql.py
astro/databases/postgres.py
astro/databases/snowflake.py
astro/databases/sqlite.py
astro/databases/aws/__init__.py
astro/databases/aws/redshift.py
astro/databases/databricks/__init__.py
astro/databases/databricks/api_utils.py
astro/databases/databricks/delta.py
astro/databases/databricks/load_options.py
astro/databases/databricks/load_file/__init__.py
astro/databases/databricks/load_file/load_file_job.py
astro/databases/databricks/load_file/load_file_python_code_generator.py
astro/databases/databricks/load_file/jinja_templates/autoloader.py.jinja2
astro/databases/databricks/load_file/jinja_templates/copy_into.py.jinja2
astro/databases/databricks/load_file/jinja_templates/load_file_to_delta.py.jinja2
astro/databases/databricks/load_file/jinja_templates/load_secrets.py.jinja2
astro/databases/google/__init__.py
astro/databases/google/bigquery.py
astro/dataframes/__init__.py
astro/dataframes/load_options.py
astro/dataframes/pandas.py
astro/files/__init__.py
astro/files/base.py
astro/files/locations/__init__.py
astro/files/locations/base.py
astro/files/locations/ftp.py
astro/files/locations/http.py
astro/files/locations/local.py
astro/files/locations/sftp.py
astro/files/locations/amazon/__init__.py
astro/files/locations/amazon/s3.py
astro/files/locations/azure/__init__.py
astro/files/locations/azure/wasb.py
astro/files/locations/google/__init__.py
astro/files/locations/google/gcs.py
astro/files/locations/google/gdrive.py
astro/files/operators/__init__.py
astro/files/operators/files.py
astro/files/types/__init__.py
astro/files/types/base.py
astro_sdk_python-1.7.0.dist-info/entry_points.txt
astro_sdk_python-1.7.0.dist-info/WHEEL
astro_sdk_python-1.7.0.dist-info/METADATA
astro_sdk_python-1.7.0.dist-info/RECORD
