Metadata-Version: 2.1
Name: astro-sdk-python
Version: 1.7.0
Summary: Astro SDK allows rapid and clean development of {Extract, Load, Transform} workflows using Python and SQL, powered by Apache Airflow.
Keywords: airflow,provider,astronomer,sql,decorator,task flow,elt,etl,dag
Author-email: Astronomer <humans@astronomer.io>
Requires-Python: >=3.7
Classifier: Development Status :: 5 - Production/Stable
Classifier: License :: OSI Approved :: Apache Software License
Classifier: Topic :: Database
Classifier: Framework :: Apache Airflow
Classifier: Programming Language :: Python :: 3
Classifier: Programming Language :: Python :: 3 :: Only
Classifier: Programming Language :: Python :: 3.7
Classifier: Programming Language :: Python :: 3.8
Classifier: Programming Language :: Python :: 3.9
Classifier: Programming Language :: Python :: 3.10
Classifier: Programming Language :: Python :: 3.11
Requires-Dist: apache-airflow>=2.0
Requires-Dist: attrs>=20.3.0
Requires-Dist: pandas
Requires-Dist: pyarrow
Requires-Dist: python-frontmatter
Requires-Dist: smart-open
Requires-Dist: SQLAlchemy>=1.3.18
Requires-Dist: cached_property>=1.5.0;python_version<='3.7'
Requires-Dist: apache-airflow-providers-amazon ; extra == "all"
Requires-Dist: apache-airflow-providers-google>=6.4.0 ; extra == "all"
Requires-Dist: apache-airflow-providers-ftp ; extra == "all"
Requires-Dist: apache-airflow-providers-postgres ; extra == "all"
Requires-Dist: apache-airflow-providers-snowflake ; extra == "all"
Requires-Dist: apache-airflow-providers-sftp ; extra == "all"
Requires-Dist: smart-open[all]>=5.2.1 ; extra == "all"
Requires-Dist: snowflake-connector-python[pandas] ; extra == "all"
Requires-Dist: snowflake-sqlalchemy>=1.2.0 ; extra == "all"
Requires-Dist: sqlalchemy-bigquery>=1.3.0 ; extra == "all"
Requires-Dist: databricks-cli ; extra == "all"
Requires-Dist: apache-airflow-providers-databricks ; extra == "all"
Requires-Dist: databricks-sql-connector<2.9.0 ; extra == "all"
Requires-Dist: s3fs ; extra == "all"
Requires-Dist: protobuf ; extra == "all"
Requires-Dist: openlineage-airflow>=0.17.0 ; extra == "all"
Requires-Dist: apache-airflow-providers-microsoft-azure ; extra == "all"
Requires-Dist: azure-storage-blob ; extra == "all"
Requires-Dist: apache-airflow-providers-microsoft-mssql>=3.2 ; extra == "all"
Requires-Dist: airflow-provider-duckdb>=0.0.2 ; extra == "all"
Requires-Dist: apache-airflow-providers-mysql ; extra == "all"
Requires-Dist: apache-airflow-providers-amazon>=5.0.0 ; extra == "amazon"
Requires-Dist: s3fs ; extra == "amazon"
Requires-Dist: smart-open[s3]>=5.2.1 ; extra == "amazon"
Requires-Dist: apache-airflow-providers-microsoft-azure ; extra == "azure"
Requires-Dist: azure-storage-blob ; extra == "azure"
Requires-Dist: smart-open[azure]>=5.2.1 ; extra == "azure"
Requires-Dist: databricks-cli ; extra == "databricks"
Requires-Dist: apache-airflow-providers-databricks ; extra == "databricks"
Requires-Dist: databricks-sql-connector<2.9.0 ; extra == "databricks"
Requires-Dist: myst-parser>=0.17 ; extra == "doc"
Requires-Dist: sphinx>=4.4.0 ; extra == "doc"
Requires-Dist: sphinx-autoapi==2.0.0 ; extra == "doc"
Requires-Dist: sphinx-rtd-theme ; extra == "doc"
Requires-Dist: airflow-provider-duckdb>=0.0.2 ; extra == "duckdb"
Requires-Dist: apache-airflow-providers-ftp>=3.0.0 ; extra == "ftp"
Requires-Dist: smart-open>=5.2.1 ; extra == "ftp"
Requires-Dist: protobuf ; extra == "google"
Requires-Dist: apache-airflow-providers-google>=6.4.0 ; extra == "google"
Requires-Dist: sqlalchemy-bigquery>=1.3.0 ; extra == "google"
Requires-Dist: smart-open[gcs]>=5.2.1 ; extra == "google"
Requires-Dist: apache-airflow-providers-microsoft-mssql>=3.2 ; extra == "mssql"
Requires-Dist: apache-airflow-providers-mysql ; extra == "mysql"
Requires-Dist: openlineage-airflow>=0.17.0 ; extra == "openlineage"
Requires-Dist: apache-airflow-providers-postgres ; extra == "postgres"
Requires-Dist: apache-airflow-providers-sftp>=4.0.0 ; extra == "sftp"
Requires-Dist: smart-open[ssh]>=5.2.1 ; extra == "sftp"
Requires-Dist: apache-airflow-providers-snowflake ; extra == "snowflake"
Requires-Dist: snowflake-sqlalchemy>=1.2.0 ; extra == "snowflake"
Requires-Dist: snowflake-connector-python[pandas] ; extra == "snowflake"
Requires-Dist: pytest>=6.0 ; extra == "tests"
Requires-Dist: pytest-split ; extra == "tests"
Requires-Dist: pytest-dotenv ; extra == "tests"
Requires-Dist: requests-mock ; extra == "tests"
Requires-Dist: pytest-cov ; extra == "tests"
Requires-Dist: pytest-describe ; extra == "tests"
Requires-Dist: types-requests ; extra == "tests"
Requires-Dist: mypy ; extra == "tests"
Requires-Dist: sqlalchemy-stubs ; extra == "tests"
Project-URL: Documentation, https://astro-sdk-python.rtfd.io/
Project-URL: Home, https://astronomer.io/
Project-URL: Source, https://github.com/astronomer/astro-sdk/tree/main/python-sdk
Provides-Extra: all
Provides-Extra: amazon
Provides-Extra: azure
Provides-Extra: databricks
Provides-Extra: doc
Provides-Extra: duckdb
Provides-Extra: ftp
Provides-Extra: google
Provides-Extra: mssql
Provides-Extra: mysql
Provides-Extra: openlineage
Provides-Extra: postgres
Provides-Extra: sftp
Provides-Extra: snowflake
Provides-Extra: tests
